pyhive/__init__.py
pyhive/types.py
pyhive/cli/__init__.py
pyhive/cli/main.py
pyhive/client/__init__.py
pyhive/client/assignment_responses.py
pyhive/client/assignments.py
pyhive/client/classes.py
pyhive/client/client_shared.py
pyhive/client/exercises.py
pyhive/client/fields.py
pyhive/client/help.py
pyhive/client/modules.py
pyhive/client/programs.py
pyhive/client/queues.py
pyhive/client/subjects.py
pyhive/client/users.py
pyhive/client/utils.py
pyhive/client/version.py
pyhive/src/__init__.py
pyhive/src/_generated_versions.py
pyhive/src/api_versions.py
pyhive/src/authenticated_hive_client.py
pyhive/src/types/__init__.py
pyhive/src/types/assignment.py
pyhive/src/types/assignment_response.py
pyhive/src/types/assignment_response_content.py
pyhive/src/types/autocheck_status.py
pyhive/src/types/class_.py
pyhive/src/types/common.py
pyhive/src/types/core_item.py
pyhive/src/types/event.py
pyhive/src/types/event_attendees_type_0_item.py
pyhive/src/types/event_color.py
pyhive/src/types/exercise.py
pyhive/src/types/form_field.py
pyhive/src/types/help_.py
pyhive/src/types/help_response.py
pyhive/src/types/help_response_segel_nested.py
pyhive/src/types/module.py
pyhive/src/types/notification_nested.py
pyhive/src/types/program.py
pyhive/src/types/queue.py
pyhive/src/types/queue_item.py
pyhive/src/types/subject.py
pyhive/src/types/tag.py
pyhive/src/types/user.py
pyhive/src/types/enums/__init__.py
pyhive/src/types/enums/action_enum.py
pyhive/src/types/enums/assignment_response_type_enum.py
pyhive/src/types/enums/assignment_status_enum.py
pyhive/src/types/enums/class_type_enum.py
pyhive/src/types/enums/clearance_enum.py
pyhive/src/types/enums/event_type_enum.py
pyhive/src/types/enums/exercise_patbas_enum.py
pyhive/src/types/enums/exercise_preview_types.py
pyhive/src/types/enums/form_field_type_enum.py
pyhive/src/types/enums/gender_enum.py
pyhive/src/types/enums/help_response_type_enum.py
pyhive/src/types/enums/help_status_enum.py
pyhive/src/types/enums/help_type_enum.py
pyhivelms-1.1.1.dist-info/METADATA
pyhivelms-1.1.1.dist-info/WHEEL
pyhivelms-1.1.1.dist-info/entry_points.txt
pyhivelms-1.1.1.dist-info/RECORD
