Metadata-Version: 2.4
Name: PyHiveLMS
Version: 1.1.1
Summary: Python bindings for Hive
Author-email: "Michael K. Steinberg" <m.kuper.steinberg@gmail.com>
Requires-Python: >=3.11.0
Requires-Dist: attrs>=25.4.0
Requires-Dist: httpx>=0.28.1
Requires-Dist: python-dateutil>=2.9.0
Requires-Dist: typer==0.20.0
